{
  "type": "Program",
  "body": [
    {
      "type": "ImportDeclaration",
      "specifiers": [
        {
          "type": "ImportDefaultSpecifier",
          "local": {
            "type": "Identifier",
            "name": "BaseViewListItem",
            "range": [
              7,
              23
            ],
            "loc": {
              "start": {
                "line": 1,
                "column": 7
              },
              "end": {
                "line": 1,
                "column": 23
              }
            }
          },
          "range": [
            7,
            23
          ],
          "loc": {
            "start": {
              "line": 1,
              "column": 7
            },
            "end": {
              "line": 1,
              "column": 23
            }
          }
        }
      ],
      "source": {
        "type": "Literal",
        "value": "../../BaseViewListItem",
        "raw": "'../../BaseViewListItem'",
        "range": [
          29,
          53
        ],
        "loc": {
          "start": {
            "line": 1,
            "column": 29
          },
          "end": {
            "line": 1,
            "column": 53
          }
        }
      },
      "range": [
        0,
        54
      ],
      "loc": {
        "start": {
          "line": 1,
          "column": 0
        },
        "end": {
          "line": 1,
          "column": 54
        }
      }
    },
    {
      "type": "ImportDeclaration",
      "specifiers": [
        {
          "type": "ImportDefaultSpecifier",
          "local": {
            "type": "Identifier",
            "name": "RODAN_EVENTS",
            "range": [
              62,
              74
            ],
            "loc": {
              "start": {
                "line": 2,
                "column": 7
              },
              "end": {
                "line": 2,
                "column": 19
              }
            }
          },
          "range": [
            62,
            74
          ],
          "loc": {
            "start": {
              "line": 2,
              "column": 7
            },
            "end": {
              "line": 2,
              "column": 19
            }
          }
        }
      ],
      "source": {
        "type": "Literal",
        "value": "../../../../../Shared/RODAN_EVENTS",
        "raw": "'../../../../../Shared/RODAN_EVENTS'",
        "range": [
          80,
          116
        ],
        "loc": {
          "start": {
            "line": 2,
            "column": 25
          },
          "end": {
            "line": 2,
            "column": 61
          }
        }
      },
      "range": [
        55,
        117
      ],
      "loc": {
        "start": {
          "line": 2,
          "column": 0
        },
        "end": {
          "line": 2,
          "column": 62
        }
      }
    },
    {
      "type": "ImportDeclaration",
      "specifiers": [
        {
          "type": "ImportDefaultSpecifier",
          "local": {
            "type": "Identifier",
            "name": "Radio",
            "range": [
              125,
              130
            ],
            "loc": {
              "start": {
                "line": 3,
                "column": 7
              },
              "end": {
                "line": 3,
                "column": 12
              }
            }
          },
          "range": [
            125,
            130
          ],
          "loc": {
            "start": {
              "line": 3,
              "column": 7
            },
            "end": {
              "line": 3,
              "column": 12
            }
          }
        }
      ],
      "source": {
        "type": "Literal",
        "value": "backbone.radio",
        "raw": "'backbone.radio'",
        "range": [
          136,
          152
        ],
        "loc": {
          "start": {
            "line": 3,
            "column": 18
          },
          "end": {
            "line": 3,
            "column": 34
          }
        }
      },
      "range": [
        118,
        153
      ],
      "loc": {
        "start": {
          "line": 3,
          "column": 0
        },
        "end": {
          "line": 3,
          "column": 35
        }
      },
      "trailingComments": [
        {
          "type": "Block",
          "value": "*\n * OutputPort list item view.\n ",
          "range": [
            155,
            192
          ],
          "loc": {
            "start": {
              "line": 5,
              "column": 0
            },
            "end": {
              "line": 7,
              "column": 3
            }
          }
        }
      ]
    },
    {
      "type": "ExportDefaultDeclaration",
      "declaration": {
        "type": "ClassDeclaration",
        "id": {
          "type": "Identifier",
          "name": "ViewOutputPortListItem",
          "range": [
            214,
            236
          ],
          "loc": {
            "start": {
              "line": 8,
              "column": 21
            },
            "end": {
              "line": 8,
              "column": 43
            }
          }
        },
        "superClass": {
          "type": "Identifier",
          "name": "BaseViewListItem",
          "range": [
            245,
            261
          ],
          "loc": {
            "start": {
              "line": 8,
              "column": 52
            },
            "end": {
              "line": 8,
              "column": 68
            }
          }
        },
        "body": {
          "type": "ClassBody",
          "body": [
            {
              "type": "MethodDefinition",
              "key": {
                "type": "Identifier",
                "name": "initialize",
                "range": [
                  673,
                  683
                ],
                "loc": {
                  "start": {
                    "line": 18,
                    "column": 4
                  },
                  "end": {
                    "line": 18,
                    "column": 14
                  }
                }
              },
              "value": {
                "type": "FunctionExpression",
                "id": null,
                "params": [
                  {
                    "type": "Identifier",
                    "name": "options",
                    "range": [
                      684,
                      691
                    ],
                    "loc": {
                      "start": {
                        "line": 18,
                        "column": 15
                      },
                      "end": {
                        "line": 18,
                        "column": 22
                      }
                    }
                  }
                ],
                "body": {
                  "type": "BlockStatement",
                  "body": [
                    {
                      "type": "ExpressionStatement",
                      "expression": {
                        "type": "AssignmentExpression",
                        "operator": "=",
                        "left": {
                          "type": "MemberExpression",
                          "computed": false,
                          "object": {
                            "type": "ThisExpression",
                            "range": [
                              707,
                              711
                            ],
                            "loc": {
                              "start": {
                                "line": 20,
                                "column": 8
                              },
                              "end": {
                                "line": 20,
                                "column": 12
                              }
                            }
                          },
                          "property": {
                            "type": "Identifier",
                            "name": "_workflow",
                            "range": [
                              712,
                              721
                            ],
                            "loc": {
                              "start": {
                                "line": 20,
                                "column": 13
                              },
                              "end": {
                                "line": 20,
                                "column": 22
                              }
                            }
                          },
                          "range": [
                            707,
                            721
                          ],
                          "loc": {
                            "start": {
                              "line": 20,
                              "column": 8
                            },
                            "end": {
                              "line": 20,
                              "column": 22
                            }
                          }
                        },
                        "right": {
                          "type": "MemberExpression",
                          "computed": false,
                          "object": {
                            "type": "Identifier",
                            "name": "options",
                            "range": [
                              724,
                              731
                            ],
                            "loc": {
                              "start": {
                                "line": 20,
                                "column": 25
                              },
                              "end": {
                                "line": 20,
                                "column": 32
                              }
                            }
                          },
                          "property": {
                            "type": "Identifier",
                            "name": "workflow",
                            "range": [
                              732,
                              740
                            ],
                            "loc": {
                              "start": {
                                "line": 20,
                                "column": 33
                              },
                              "end": {
                                "line": 20,
                                "column": 41
                              }
                            }
                          },
                          "range": [
                            724,
                            740
                          ],
                          "loc": {
                            "start": {
                              "line": 20,
                              "column": 25
                            },
                            "end": {
                              "line": 20,
                              "column": 41
                            }
                          }
                        },
                        "range": [
                          707,
                          740
                        ],
                        "loc": {
                          "start": {
                            "line": 20,
                            "column": 8
                          },
                          "end": {
                            "line": 20,
                            "column": 41
                          }
                        }
                      },
                      "range": [
                        707,
                        741
                      ],
                      "loc": {
                        "start": {
                          "line": 20,
                          "column": 8
                        },
                        "end": {
                          "line": 20,
                          "column": 42
                        }
                      }
                    },
                    {
                      "type": "ExpressionStatement",
                      "expression": {
                        "type": "AssignmentExpression",
                        "operator": "=",
                        "left": {
                          "type": "MemberExpression",
                          "computed": false,
                          "object": {
                            "type": "ThisExpression",
                            "range": [
                              750,
                              754
                            ],
                            "loc": {
                              "start": {
                                "line": 21,
                                "column": 8
                              },
                              "end": {
                                "line": 21,
                                "column": 12
                              }
                            }
                          },
                          "property": {
                            "type": "Identifier",
                            "name": "_workflowJob",
                            "range": [
                              755,
                              767
                            ],
                            "loc": {
                              "start": {
                                "line": 21,
                                "column": 13
                              },
                              "end": {
                                "line": 21,
                                "column": 25
                              }
                            }
                          },
                          "range": [
                            750,
                            767
                          ],
                          "loc": {
                            "start": {
                              "line": 21,
                              "column": 8
                            },
                            "end": {
                              "line": 21,
                              "column": 25
                            }
                          }
                        },
                        "right": {
                          "type": "MemberExpression",
                          "computed": false,
                          "object": {
                            "type": "Identifier",
                            "name": "options",
                            "range": [
                              770,
                              777
                            ],
                            "loc": {
                              "start": {
                                "line": 21,
                                "column": 28
                              },
                              "end": {
                                "line": 21,
                                "column": 35
                              }
                            }
                          },
                          "property": {
                            "type": "Identifier",
                            "name": "workflowjob",
                            "range": [
                              778,
                              789
                            ],
                            "loc": {
                              "start": {
                                "line": 21,
                                "column": 36
                              },
                              "end": {
                                "line": 21,
                                "column": 47
                              }
                            }
                          },
                          "range": [
                            770,
                            789
                          ],
                          "loc": {
                            "start": {
                              "line": 21,
                              "column": 28
                            },
                            "end": {
                              "line": 21,
                              "column": 47
                            }
                          }
                        },
                        "range": [
                          750,
                          789
                        ],
                        "loc": {
                          "start": {
                            "line": 21,
                            "column": 8
                          },
                          "end": {
                            "line": 21,
                            "column": 47
                          }
                        }
                      },
                      "range": [
                        750,
                        790
                      ],
                      "loc": {
                        "start": {
                          "line": 21,
                          "column": 8
                        },
                        "end": {
                          "line": 21,
                          "column": 48
                        }
                      }
                    }
                  ],
                  "range": [
                    697,
                    796
                  ],
                  "loc": {
                    "start": {
                      "line": 19,
                      "column": 4
                    },
                    "end": {
                      "line": 22,
                      "column": 5
                    }
                  }
                },
                "generator": false,
                "expression": false,
                "range": [
                  683,
                  796
                ],
                "loc": {
                  "start": {
                    "line": 18,
                    "column": 14
                  },
                  "end": {
                    "line": 22,
                    "column": 5
                  }
                }
              },
              "kind": "method",
              "computed": false,
              "range": [
                673,
                796
              ],
              "loc": {
                "start": {
                  "line": 18,
                  "column": 4
                },
                "end": {
                  "line": 22,
                  "column": 5
                }
              },
              "leadingComments": [
                {
                  "type": "Line",
                  "value": "/////////////////////////////////////////////////////////////////////////////////////",
                  "range": [
                    264,
                    351
                  ],
                  "loc": {
                    "start": {
                      "line": 10,
                      "column": 0
                    },
                    "end": {
                      "line": 10,
                      "column": 87
                    }
                  }
                },
                {
                  "type": "Line",
                  "value": " PUBLIC METHODS",
                  "range": [
                    352,
                    369
                  ],
                  "loc": {
                    "start": {
                      "line": 11,
                      "column": 0
                    },
                    "end": {
                      "line": 11,
                      "column": 17
                    }
                  }
                },
                {
                  "type": "Line",
                  "value": "/////////////////////////////////////////////////////////////////////////////////////",
                  "range": [
                    370,
                    457
                  ],
                  "loc": {
                    "start": {
                      "line": 12,
                      "column": 0
                    },
                    "end": {
                      "line": 12,
                      "column": 87
                    }
                  }
                },
                {
                  "type": "Block",
                  "value": "*\n     * Initializes the instance.\n     *\n     * @param {object} options Marionette.View options object; 'options.workflow' (Workflow) and 'options.workflowjob' (WorkflowJob) must also be provided\n     ",
                  "range": [
                    462,
                    668
                  ],
                  "loc": {
                    "start": {
                      "line": 13,
                      "column": 4
                    },
                    "end": {
                      "line": 17,
                      "column": 7
                    }
                  }
                }
              ],
              "trailingComments": [
                {
                  "type": "Line",
                  "value": "/////////////////////////////////////////////////////////////////////////////////////",
                  "range": [
                    798,
                    885
                  ],
                  "loc": {
                    "start": {
                      "line": 24,
                      "column": 0
                    },
                    "end": {
                      "line": 24,
                      "column": 87
                    }
                  }
                },
                {
                  "type": "Line",
                  "value": " PRIVATE METHODS",
                  "range": [
                    886,
                    904
                  ],
                  "loc": {
                    "start": {
                      "line": 25,
                      "column": 0
                    },
                    "end": {
                      "line": 25,
                      "column": 18
                    }
                  }
                },
                {
                  "type": "Line",
                  "value": "/////////////////////////////////////////////////////////////////////////////////////",
                  "range": [
                    905,
                    992
                  ],
                  "loc": {
                    "start": {
                      "line": 26,
                      "column": 0
                    },
                    "end": {
                      "line": 26,
                      "column": 87
                    }
                  }
                },
                {
                  "type": "Block",
                  "value": "*\n     * Handle delete.\n     ",
                  "range": [
                    997,
                    1030
                  ],
                  "loc": {
                    "start": {
                      "line": 27,
                      "column": 4
                    },
                    "end": {
                      "line": 29,
                      "column": 7
                    }
                  }
                }
              ],
              "static": false
            },
            {
              "type": "MethodDefinition",
              "key": {
                "type": "Identifier",
                "name": "_handleButtonDelete",
                "range": [
                  1035,
                  1054
                ],
                "loc": {
                  "start": {
                    "line": 30,
                    "column": 4
                  },
                  "end": {
                    "line": 30,
                    "column": 23
                  }
                }
              },
              "value": {
                "type": "FunctionExpression",
                "id": null,
                "params": [],
                "body": {
                  "type": "BlockStatement",
                  "body": [
                    {
                      "type": "ExpressionStatement",
                      "expression": {
                        "type": "CallExpression",
                        "callee": {
                          "type": "MemberExpression",
                          "computed": false,
                          "object": {
                            "type": "CallExpression",
                            "callee": {
                              "type": "MemberExpression",
                              "computed": false,
                              "object": {
                                "type": "Identifier",
                                "name": "Radio",
                                "range": [
                                  1071,
                                  1076
                                ],
                                "loc": {
                                  "start": {
                                    "line": 32,
                                    "column": 8
                                  },
                                  "end": {
                                    "line": 32,
                                    "column": 13
                                  }
                                }
                              },
                              "property": {
                                "type": "Identifier",
                                "name": "channel",
                                "range": [
                                  1077,
                                  1084
                                ],
                                "loc": {
                                  "start": {
                                    "line": 32,
                                    "column": 14
                                  },
                                  "end": {
                                    "line": 32,
                                    "column": 21
                                  }
                                }
                              },
                              "range": [
                                1071,
                                1084
                              ],
                              "loc": {
                                "start": {
                                  "line": 32,
                                  "column": 8
                                },
                                "end": {
                                  "line": 32,
                                  "column": 21
                                }
                              }
                            },
                            "arguments": [
                              {
                                "type": "Literal",
                                "value": "rodan",
                                "raw": "'rodan'",
                                "range": [
                                  1085,
                                  1092
                                ],
                                "loc": {
                                  "start": {
                                    "line": 32,
                                    "column": 22
                                  },
                                  "end": {
                                    "line": 32,
                                    "column": 29
                                  }
                                }
                              }
                            ],
                            "range": [
                              1071,
                              1093
                            ],
                            "loc": {
                              "start": {
                                "line": 32,
                                "column": 8
                              },
                              "end": {
                                "line": 32,
                                "column": 30
                              }
                            }
                          },
                          "property": {
                            "type": "Identifier",
                            "name": "request",
                            "range": [
                              1094,
                              1101
                            ],
                            "loc": {
                              "start": {
                                "line": 32,
                                "column": 31
                              },
                              "end": {
                                "line": 32,
                                "column": 38
                              }
                            }
                          },
                          "range": [
                            1071,
                            1101
                          ],
                          "loc": {
                            "start": {
                              "line": 32,
                              "column": 8
                            },
                            "end": {
                              "line": 32,
                              "column": 38
                            }
                          }
                        },
                        "arguments": [
                          {
                            "type": "MemberExpression",
                            "computed": false,
                            "object": {
                              "type": "Identifier",
                              "name": "RODAN_EVENTS",
                              "range": [
                                1102,
                                1114
                              ],
                              "loc": {
                                "start": {
                                  "line": 32,
                                  "column": 39
                                },
                                "end": {
                                  "line": 32,
                                  "column": 51
                                }
                              }
                            },
                            "property": {
                              "type": "Identifier",
                              "name": "REQUEST__WORKFLOWBUILDER_REMOVE_OUTPUTPORT",
                              "range": [
                                1115,
                                1157
                              ],
                              "loc": {
                                "start": {
                                  "line": 32,
                                  "column": 52
                                },
                                "end": {
                                  "line": 32,
                                  "column": 94
                                }
                              }
                            },
                            "range": [
                              1102,
                              1157
                            ],
                            "loc": {
                              "start": {
                                "line": 32,
                                "column": 39
                              },
                              "end": {
                                "line": 32,
                                "column": 94
                              }
                            }
                          },
                          {
                            "type": "ObjectExpression",
                            "properties": [
                              {
                                "type": "Property",
                                "key": {
                                  "type": "Identifier",
                                  "name": "outputport",
                                  "range": [
                                    1160,
                                    1170
                                  ],
                                  "loc": {
                                    "start": {
                                      "line": 32,
                                      "column": 97
                                    },
                                    "end": {
                                      "line": 32,
                                      "column": 107
                                    }
                                  }
                                },
                                "value": {
                                  "type": "MemberExpression",
                                  "computed": false,
                                  "object": {
                                    "type": "ThisExpression",
                                    "range": [
                                      1172,
                                      1176
                                    ],
                                    "loc": {
                                      "start": {
                                        "line": 32,
                                        "column": 109
                                      },
                                      "end": {
                                        "line": 32,
                                        "column": 113
                                      }
                                    }
                                  },
                                  "property": {
                                    "type": "Identifier",
                                    "name": "model",
                                    "range": [
                                      1177,
                                      1182
                                    ],
                                    "loc": {
                                      "start": {
                                        "line": 32,
                                        "column": 114
                                      },
                                      "end": {
                                        "line": 32,
                                        "column": 119
                                      }
                                    }
                                  },
                                  "range": [
                                    1172,
                                    1182
                                  ],
                                  "loc": {
                                    "start": {
                                      "line": 32,
                                      "column": 109
                                    },
                                    "end": {
                                      "line": 32,
                                      "column": 119
                                    }
                                  }
                                },
                                "kind": "init",
                                "method": false,
                                "shorthand": false,
                                "computed": false,
                                "range": [
                                  1160,
                                  1182
                                ],
                                "loc": {
                                  "start": {
                                    "line": 32,
                                    "column": 97
                                  },
                                  "end": {
                                    "line": 32,
                                    "column": 119
                                  }
                                }
                              },
                              {
                                "type": "Property",
                                "key": {
                                  "type": "Identifier",
                                  "name": "workflow",
                                  "range": [
                                    1184,
                                    1192
                                  ],
                                  "loc": {
                                    "start": {
                                      "line": 32,
                                      "column": 121
                                    },
                                    "end": {
                                      "line": 32,
                                      "column": 129
                                    }
                                  }
                                },
                                "value": {
                                  "type": "MemberExpression",
                                  "computed": false,
                                  "object": {
                                    "type": "ThisExpression",
                                    "range": [
                                      1194,
                                      1198
                                    ],
                                    "loc": {
                                      "start": {
                                        "line": 32,
                                        "column": 131
                                      },
                                      "end": {
                                        "line": 32,
                                        "column": 135
                                      }
                                    }
                                  },
                                  "property": {
                                    "type": "Identifier",
                                    "name": "_workflow",
                                    "range": [
                                      1199,
                                      1208
                                    ],
                                    "loc": {
                                      "start": {
                                        "line": 32,
                                        "column": 136
                                      },
                                      "end": {
                                        "line": 32,
                                        "column": 145
                                      }
                                    }
                                  },
                                  "range": [
                                    1194,
                                    1208
                                  ],
                                  "loc": {
                                    "start": {
                                      "line": 32,
                                      "column": 131
                                    },
                                    "end": {
                                      "line": 32,
                                      "column": 145
                                    }
                                  }
                                },
                                "kind": "init",
                                "method": false,
                                "shorthand": false,
                                "computed": false,
                                "range": [
                                  1184,
                                  1208
                                ],
                                "loc": {
                                  "start": {
                                    "line": 32,
                                    "column": 121
                                  },
                                  "end": {
                                    "line": 32,
                                    "column": 145
                                  }
                                }
                              },
                              {
                                "type": "Property",
                                "key": {
                                  "type": "Identifier",
                                  "name": "workflowjob",
                                  "range": [
                                    1210,
                                    1221
                                  ],
                                  "loc": {
                                    "start": {
                                      "line": 32,
                                      "column": 147
                                    },
                                    "end": {
                                      "line": 32,
                                      "column": 158
                                    }
                                  }
                                },
                                "value": {
                                  "type": "MemberExpression",
                                  "computed": false,
                                  "object": {
                                    "type": "ThisExpression",
                                    "range": [
                                      1223,
                                      1227
                                    ],
                                    "loc": {
                                      "start": {
                                        "line": 32,
                                        "column": 160
                                      },
                                      "end": {
                                        "line": 32,
                                        "column": 164
                                      }
                                    }
                                  },
                                  "property": {
                                    "type": "Identifier",
                                    "name": "_workflowJob",
                                    "range": [
                                      1228,
                                      1240
                                    ],
                                    "loc": {
                                      "start": {
                                        "line": 32,
                                        "column": 165
                                      },
                                      "end": {
                                        "line": 32,
                                        "column": 177
                                      }
                                    }
                                  },
                                  "range": [
                                    1223,
                                    1240
                                  ],
                                  "loc": {
                                    "start": {
                                      "line": 32,
                                      "column": 160
                                    },
                                    "end": {
                                      "line": 32,
                                      "column": 177
                                    }
                                  }
                                },
                                "kind": "init",
                                "method": false,
                                "shorthand": false,
                                "computed": false,
                                "range": [
                                  1210,
                                  1240
                                ],
                                "loc": {
                                  "start": {
                                    "line": 32,
                                    "column": 147
                                  },
                                  "end": {
                                    "line": 32,
                                    "column": 177
                                  }
                                }
                              }
                            ],
                            "range": [
                              1159,
                              1241
                            ],
                            "loc": {
                              "start": {
                                "line": 32,
                                "column": 96
                              },
                              "end": {
                                "line": 32,
                                "column": 178
                              }
                            }
                          }
                        ],
                        "range": [
                          1071,
                          1242
                        ],
                        "loc": {
                          "start": {
                            "line": 32,
                            "column": 8
                          },
                          "end": {
                            "line": 32,
                            "column": 179
                          }
                        }
                      },
                      "range": [
                        1071,
                        1243
                      ],
                      "loc": {
                        "start": {
                          "line": 32,
                          "column": 8
                        },
                        "end": {
                          "line": 32,
                          "column": 180
                        }
                      }
                    }
                  ],
                  "range": [
                    1061,
                    1249
                  ],
                  "loc": {
                    "start": {
                      "line": 31,
                      "column": 4
                    },
                    "end": {
                      "line": 33,
                      "column": 5
                    }
                  }
                },
                "generator": false,
                "expression": false,
                "range": [
                  1054,
                  1249
                ],
                "loc": {
                  "start": {
                    "line": 30,
                    "column": 23
                  },
                  "end": {
                    "line": 33,
                    "column": 5
                  }
                }
              },
              "kind": "method",
              "computed": false,
              "range": [
                1035,
                1249
              ],
              "loc": {
                "start": {
                  "line": 30,
                  "column": 4
                },
                "end": {
                  "line": 33,
                  "column": 5
                }
              },
              "leadingComments": [
                {
                  "type": "Line",
                  "value": "/////////////////////////////////////////////////////////////////////////////////////",
                  "range": [
                    798,
                    885
                  ],
                  "loc": {
                    "start": {
                      "line": 24,
                      "column": 0
                    },
                    "end": {
                      "line": 24,
                      "column": 87
                    }
                  }
                },
                {
                  "type": "Line",
                  "value": " PRIVATE METHODS",
                  "range": [
                    886,
                    904
                  ],
                  "loc": {
                    "start": {
                      "line": 25,
                      "column": 0
                    },
                    "end": {
                      "line": 25,
                      "column": 18
                    }
                  }
                },
                {
                  "type": "Line",
                  "value": "/////////////////////////////////////////////////////////////////////////////////////",
                  "range": [
                    905,
                    992
                  ],
                  "loc": {
                    "start": {
                      "line": 26,
                      "column": 0
                    },
                    "end": {
                      "line": 26,
                      "column": 87
                    }
                  }
                },
                {
                  "type": "Block",
                  "value": "*\n     * Handle delete.\n     ",
                  "range": [
                    997,
                    1030
                  ],
                  "loc": {
                    "start": {
                      "line": 27,
                      "column": 4
                    },
                    "end": {
                      "line": 29,
                      "column": 7
                    }
                  }
                }
              ],
              "static": false
            }
          ],
          "range": [
            262,
            1251
          ],
          "loc": {
            "start": {
              "line": 9,
              "column": 0
            },
            "end": {
              "line": 34,
              "column": 1
            }
          }
        },
        "range": [
          208,
          1251
        ],
        "loc": {
          "start": {
            "line": 8,
            "column": 15
          },
          "end": {
            "line": 34,
            "column": 1
          }
        },
        "leadingComments": [
          {
            "type": "Block",
            "value": "*\n * OutputPort list item view.\n ",
            "range": [
              155,
              192
            ],
            "loc": {
              "start": {
                "line": 5,
                "column": 0
              },
              "end": {
                "line": 7,
                "column": 3
              }
            }
          }
        ],
        "trailingComments": []
      },
      "range": [
        193,
        1251
      ],
      "loc": {
        "start": {
          "line": 8,
          "column": 0
        },
        "end": {
          "line": 34,
          "column": 1
        }
      },
      "leadingComments": [
        {
          "type": "Block",
          "value": "*\n * OutputPort list item view.\n ",
          "range": [
            155,
            192
          ],
          "loc": {
            "start": {
              "line": 5,
              "column": 0
            },
            "end": {
              "line": 7,
              "column": 3
            }
          }
        }
      ]
    },
    {
      "type": "ExpressionStatement",
      "expression": {
        "type": "AssignmentExpression",
        "operator": "=",
        "left": {
          "type": "MemberExpression",
          "computed": false,
          "object": {
            "type": "MemberExpression",
            "computed": false,
            "object": {
              "type": "Identifier",
              "name": "ViewOutputPortListItem",
              "range": [
                1252,
                1274
              ],
              "loc": {
                "start": {
                  "line": 35,
                  "column": 0
                },
                "end": {
                  "line": 35,
                  "column": 22
                }
              }
            },
            "property": {
              "type": "Identifier",
              "name": "prototype",
              "range": [
                1275,
                1284
              ],
              "loc": {
                "start": {
                  "line": 35,
                  "column": 23
                },
                "end": {
                  "line": 35,
                  "column": 32
                }
              }
            },
            "range": [
              1252,
              1284
            ],
            "loc": {
              "start": {
                "line": 35,
                "column": 0
              },
              "end": {
                "line": 35,
                "column": 32
              }
            }
          },
          "property": {
            "type": "Identifier",
            "name": "ui",
            "range": [
              1285,
              1287
            ],
            "loc": {
              "start": {
                "line": 35,
                "column": 33
              },
              "end": {
                "line": 35,
                "column": 35
              }
            }
          },
          "range": [
            1252,
            1287
          ],
          "loc": {
            "start": {
              "line": 35,
              "column": 0
            },
            "end": {
              "line": 35,
              "column": 35
            }
          }
        },
        "right": {
          "type": "ObjectExpression",
          "properties": [
            {
              "type": "Property",
              "key": {
                "type": "Identifier",
                "name": "buttonDelete",
                "range": [
                  1296,
                  1308
                ],
                "loc": {
                  "start": {
                    "line": 36,
                    "column": 4
                  },
                  "end": {
                    "line": 36,
                    "column": 16
                  }
                }
              },
              "value": {
                "type": "Literal",
                "value": "#button-delete",
                "raw": "'#button-delete'",
                "range": [
                  1310,
                  1326
                ],
                "loc": {
                  "start": {
                    "line": 36,
                    "column": 18
                  },
                  "end": {
                    "line": 36,
                    "column": 34
                  }
                }
              },
              "kind": "init",
              "method": false,
              "shorthand": false,
              "computed": false,
              "range": [
                1296,
                1326
              ],
              "loc": {
                "start": {
                  "line": 36,
                  "column": 4
                },
                "end": {
                  "line": 36,
                  "column": 34
                }
              }
            }
          ],
          "range": [
            1290,
            1328
          ],
          "loc": {
            "start": {
              "line": 35,
              "column": 38
            },
            "end": {
              "line": 37,
              "column": 1
            }
          }
        },
        "range": [
          1252,
          1328
        ],
        "loc": {
          "start": {
            "line": 35,
            "column": 0
          },
          "end": {
            "line": 37,
            "column": 1
          }
        }
      },
      "range": [
        1252,
        1329
      ],
      "loc": {
        "start": {
          "line": 35,
          "column": 0
        },
        "end": {
          "line": 37,
          "column": 2
        }
      }
    },
    {
      "type": "ExpressionStatement",
      "expression": {
        "type": "AssignmentExpression",
        "operator": "=",
        "left": {
          "type": "MemberExpression",
          "computed": false,
          "object": {
            "type": "MemberExpression",
            "computed": false,
            "object": {
              "type": "Identifier",
              "name": "ViewOutputPortListItem",
              "range": [
                1330,
                1352
              ],
              "loc": {
                "start": {
                  "line": 38,
                  "column": 0
                },
                "end": {
                  "line": 38,
                  "column": 22
                }
              }
            },
            "property": {
              "type": "Identifier",
              "name": "prototype",
              "range": [
                1353,
                1362
              ],
              "loc": {
                "start": {
                  "line": 38,
                  "column": 23
                },
                "end": {
                  "line": 38,
                  "column": 32
                }
              }
            },
            "range": [
              1330,
              1362
            ],
            "loc": {
              "start": {
                "line": 38,
                "column": 0
              },
              "end": {
                "line": 38,
                "column": 32
              }
            }
          },
          "property": {
            "type": "Identifier",
            "name": "events",
            "range": [
              1363,
              1369
            ],
            "loc": {
              "start": {
                "line": 38,
                "column": 33
              },
              "end": {
                "line": 38,
                "column": 39
              }
            }
          },
          "range": [
            1330,
            1369
          ],
          "loc": {
            "start": {
              "line": 38,
              "column": 0
            },
            "end": {
              "line": 38,
              "column": 39
            }
          }
        },
        "right": {
          "type": "ObjectExpression",
          "properties": [
            {
              "type": "Property",
              "key": {
                "type": "Literal",
                "value": "click @ui.buttonDelete",
                "raw": "'click @ui.buttonDelete'",
                "range": [
                  1378,
                  1402
                ],
                "loc": {
                  "start": {
                    "line": 39,
                    "column": 4
                  },
                  "end": {
                    "line": 39,
                    "column": 28
                  }
                }
              },
              "value": {
                "type": "Literal",
                "value": "_handleButtonDelete",
                "raw": "'_handleButtonDelete'",
                "range": [
                  1404,
                  1425
                ],
                "loc": {
                  "start": {
                    "line": 39,
                    "column": 30
                  },
                  "end": {
                    "line": 39,
                    "column": 51
                  }
                }
              },
              "kind": "init",
              "method": false,
              "shorthand": false,
              "computed": false,
              "range": [
                1378,
                1425
              ],
              "loc": {
                "start": {
                  "line": 39,
                  "column": 4
                },
                "end": {
                  "line": 39,
                  "column": 51
                }
              }
            }
          ],
          "range": [
            1372,
            1427
          ],
          "loc": {
            "start": {
              "line": 38,
              "column": 42
            },
            "end": {
              "line": 40,
              "column": 1
            }
          }
        },
        "range": [
          1330,
          1427
        ],
        "loc": {
          "start": {
            "line": 38,
            "column": 0
          },
          "end": {
            "line": 40,
            "column": 1
          }
        }
      },
      "range": [
        1330,
        1428
      ],
      "loc": {
        "start": {
          "line": 38,
          "column": 0
        },
        "end": {
          "line": 40,
          "column": 2
        }
      }
    },
    {
      "type": "ExpressionStatement",
      "expression": {
        "type": "AssignmentExpression",
        "operator": "=",
        "left": {
          "type": "MemberExpression",
          "computed": false,
          "object": {
            "type": "MemberExpression",
            "computed": false,
            "object": {
              "type": "Identifier",
              "name": "ViewOutputPortListItem",
              "range": [
                1429,
                1451
              ],
              "loc": {
                "start": {
                  "line": 41,
                  "column": 0
                },
                "end": {
                  "line": 41,
                  "column": 22
                }
              }
            },
            "property": {
              "type": "Identifier",
              "name": "prototype",
              "range": [
                1452,
                1461
              ],
              "loc": {
                "start": {
                  "line": 41,
                  "column": 23
                },
                "end": {
                  "line": 41,
                  "column": 32
                }
              }
            },
            "range": [
              1429,
              1461
            ],
            "loc": {
              "start": {
                "line": 41,
                "column": 0
              },
              "end": {
                "line": 41,
                "column": 32
              }
            }
          },
          "property": {
            "type": "Identifier",
            "name": "template",
            "range": [
              1462,
              1470
            ],
            "loc": {
              "start": {
                "line": 41,
                "column": 33
              },
              "end": {
                "line": 41,
                "column": 41
              }
            }
          },
          "range": [
            1429,
            1470
          ],
          "loc": {
            "start": {
              "line": 41,
              "column": 0
            },
            "end": {
              "line": 41,
              "column": 41
            }
          }
        },
        "right": {
          "type": "Literal",
          "value": "#template-main_outputport_list_item",
          "raw": "'#template-main_outputport_list_item'",
          "range": [
            1473,
            1510
          ],
          "loc": {
            "start": {
              "line": 41,
              "column": 44
            },
            "end": {
              "line": 41,
              "column": 81
            }
          }
        },
        "range": [
          1429,
          1510
        ],
        "loc": {
          "start": {
            "line": 41,
            "column": 0
          },
          "end": {
            "line": 41,
            "column": 81
          }
        }
      },
      "range": [
        1429,
        1511
      ],
      "loc": {
        "start": {
          "line": 41,
          "column": 0
        },
        "end": {
          "line": 41,
          "column": 82
        }
      }
    },
    {
      "type": "ExpressionStatement",
      "expression": {
        "type": "AssignmentExpression",
        "operator": "=",
        "left": {
          "type": "MemberExpression",
          "computed": false,
          "object": {
            "type": "MemberExpression",
            "computed": false,
            "object": {
              "type": "Identifier",
              "name": "ViewOutputPortListItem",
              "range": [
                1512,
                1534
              ],
              "loc": {
                "start": {
                  "line": 42,
                  "column": 0
                },
                "end": {
                  "line": 42,
                  "column": 22
                }
              }
            },
            "property": {
              "type": "Identifier",
              "name": "prototype",
              "range": [
                1535,
                1544
              ],
              "loc": {
                "start": {
                  "line": 42,
                  "column": 23
                },
                "end": {
                  "line": 42,
                  "column": 32
                }
              }
            },
            "range": [
              1512,
              1544
            ],
            "loc": {
              "start": {
                "line": 42,
                "column": 0
              },
              "end": {
                "line": 42,
                "column": 32
              }
            }
          },
          "property": {
            "type": "Identifier",
            "name": "tagName",
            "range": [
              1545,
              1552
            ],
            "loc": {
              "start": {
                "line": 42,
                "column": 33
              },
              "end": {
                "line": 42,
                "column": 40
              }
            }
          },
          "range": [
            1512,
            1552
          ],
          "loc": {
            "start": {
              "line": 42,
              "column": 0
            },
            "end": {
              "line": 42,
              "column": 40
            }
          }
        },
        "right": {
          "type": "Literal",
          "value": "tr",
          "raw": "'tr'",
          "range": [
            1555,
            1559
          ],
          "loc": {
            "start": {
              "line": 42,
              "column": 43
            },
            "end": {
              "line": 42,
              "column": 47
            }
          }
        },
        "range": [
          1512,
          1559
        ],
        "loc": {
          "start": {
            "line": 42,
            "column": 0
          },
          "end": {
            "line": 42,
            "column": 47
          }
        }
      },
      "range": [
        1512,
        1560
      ],
      "loc": {
        "start": {
          "line": 42,
          "column": 0
        },
        "end": {
          "line": 42,
          "column": 48
        }
      }
    }
  ],
  "sourceType": "module",
  "range": [
    0,
    1560
  ],
  "loc": {
    "start": {
      "line": 1,
      "column": 0
    },
    "end": {
      "line": 42,
      "column": 48
    }
  },
  "comments": [
    {
      "type": "Block",
      "value": "*\n * OutputPort list item view.\n ",
      "range": [
        155,
        192
      ],
      "loc": {
        "start": {
          "line": 5,
          "column": 0
        },
        "end": {
          "line": 7,
          "column": 3
        }
      }
    },
    {
      "type": "Line",
      "value": "/////////////////////////////////////////////////////////////////////////////////////",
      "range": [
        264,
        351
      ],
      "loc": {
        "start": {
          "line": 10,
          "column": 0
        },
        "end": {
          "line": 10,
          "column": 87
        }
      }
    },
    {
      "type": "Line",
      "value": " PUBLIC METHODS",
      "range": [
        352,
        369
      ],
      "loc": {
        "start": {
          "line": 11,
          "column": 0
        },
        "end": {
          "line": 11,
          "column": 17
        }
      }
    },
    {
      "type": "Line",
      "value": "/////////////////////////////////////////////////////////////////////////////////////",
      "range": [
        370,
        457
      ],
      "loc": {
        "start": {
          "line": 12,
          "column": 0
        },
        "end": {
          "line": 12,
          "column": 87
        }
      }
    },
    {
      "type": "Block",
      "value": "*\n     * Initializes the instance.\n     *\n     * @param {object} options Marionette.View options object; 'options.workflow' (Workflow) and 'options.workflowjob' (WorkflowJob) must also be provided\n     ",
      "range": [
        462,
        668
      ],
      "loc": {
        "start": {
          "line": 13,
          "column": 4
        },
        "end": {
          "line": 17,
          "column": 7
        }
      }
    },
    {
      "type": "Line",
      "value": "/////////////////////////////////////////////////////////////////////////////////////",
      "range": [
        798,
        885
      ],
      "loc": {
        "start": {
          "line": 24,
          "column": 0
        },
        "end": {
          "line": 24,
          "column": 87
        }
      }
    },
    {
      "type": "Line",
      "value": " PRIVATE METHODS",
      "range": [
        886,
        904
      ],
      "loc": {
        "start": {
          "line": 25,
          "column": 0
        },
        "end": {
          "line": 25,
          "column": 18
        }
      }
    },
    {
      "type": "Line",
      "value": "/////////////////////////////////////////////////////////////////////////////////////",
      "range": [
        905,
        992
      ],
      "loc": {
        "start": {
          "line": 26,
          "column": 0
        },
        "end": {
          "line": 26,
          "column": 87
        }
      }
    },
    {
      "type": "Block",
      "value": "*\n     * Handle delete.\n     ",
      "range": [
        997,
        1030
      ],
      "loc": {
        "start": {
          "line": 27,
          "column": 4
        },
        "end": {
          "line": 29,
          "column": 7
        }
      }
    }
  ]
}